{
    "NUR": {
        "branch": "master",
        "description": "Nix User Repository: User contributed nix packages [maintainer=@Mic92]",
        "homepage": "",
        "owner": "nix-community",
        "repo": "NUR",
        "rev": "6559855a425bbfc237029c5271215b482470de68",
        "sha256": "1il24vfd4hzc0f06d0y441fk6sy5dyx89lph8f4aris7k7nyac5h",
        "type": "tarball",
        "url": "https://github.com/nix-community/NUR/archive/6559855a425bbfc237029c5271215b482470de68.tar.gz",
        "url_template": "https://github.com/<owner>/<repo>/archive/<rev>.tar.gz"
    },
    "home-manager": {
        "branch": "master",
        "description": "Manage a user environment using Nix",
        "homepage": "",
        "owner": "rycee",
        "repo": "home-manager",
        "rev": "f6afd95ef8dd587ca15c7090eb12d3cd3d08b08a",
        "sha256": "1r386mapkimkxjkvvxvx26za2rh1ra7gyfflnliym12vj605gqri",
        "type": "tarball",
        "url": "https://github.com/rycee/home-manager/archive/f6afd95ef8dd587ca15c7090eb12d3cd3d08b08a.tar.gz",
        "url_template": "https://github.com/<owner>/<repo>/archive/<rev>.tar.gz"
    },
    "lorri": {
        "branch": "master",
        "description": "Your project's nix-env",
        "homepage": "",
        "owner": "target",
        "repo": "lorri",
        "rev": "a67121895ce3c2b4af0adc5604e756ddfc1fb2fa",
        "sha256": "0hckhg3c146zhwh48pvdw58jb4b71952i8cm3ddavdzimf2rsbhr",
        "type": "tarball",
        "url": "https://github.com/target/lorri/archive/a67121895ce3c2b4af0adc5604e756ddfc1fb2fa.tar.gz",
        "url_template": "https://github.com/<owner>/<repo>/archive/<rev>.tar.gz"
    },
    "mhnix": {
        "branch": "master",
        "description": "Nix build configuration for Matterhorn (using devnix).",
        "homepage": null,
        "owner": "kquick",
        "repo": "mhnix",
        "rev": "b2365a1734362ee1239c8ac144f3645aeed1c50f",
        "sha256": "049mjylfz13pah56xjkmh3yrsva5a2sd3yvj8qh8p04bcck6d0j0",
        "type": "tarball",
        "url": "https://github.com/kquick/mhnix/archive/b2365a1734362ee1239c8ac144f3645aeed1c50f.tar.gz",
        "url_template": "https://github.com/<owner>/<repo>/archive/<rev>.tar.gz"
    },
    "neovim": {
        "branch": "master",
        "description": "Vim-fork focused on extensibility and usability",
        "homepage": "https://neovim.io",
        "owner": "neovim",
        "repo": "neovim",
        "rev": "51b4fc4778896775da5854fe6a04d00445b72919",
        "sha256": "1abg50r45x30hdijbwa5h2n8phy20h27s72swp3yzc3sb5xxal0g",
        "type": "tarball",
        "url": "https://github.com/neovim/neovim/archive/51b4fc4778896775da5854fe6a04d00445b72919.tar.gz",
        "url_template": "https://github.com/<owner>/<repo>/archive/<rev>.tar.gz"
    },
    "niv": {
        "branch": "master",
        "description": "Easy dependency management for Nix projects",
        "homepage": "https://github.com/nmattia/niv",
        "owner": "nmattia",
        "repo": "niv",
        "rev": "f73bf8d584148677b01859677a63191c31911eae",
        "sha256": "0jlmrx633jvqrqlyhlzpvdrnim128gc81q5psz2lpp2af8p8q9qs",
        "type": "tarball",
        "url": "https://github.com/nmattia/niv/archive/f73bf8d584148677b01859677a63191c31911eae.tar.gz",
        "url_template": "https://github.com/<owner>/<repo>/archive/<rev>.tar.gz"
    },
    "nixos-hardware": {
        "branch": "master",
        "description": "A collection of NixOS modules covering hardware quirks.",
        "homepage": "",
        "owner": "NixOS",
        "repo": "nixos-hardware",
        "rev": "e58c64a03c931bfddbcae238d54ac63a67b6fa35",
        "sha256": "12awmbr1dhmn8xpz90bj0mxyjf218vspvi6mg7021q0m02k1s50s",
        "type": "tarball",
        "url": "https://github.com/NixOS/nixos-hardware/archive/e58c64a03c931bfddbcae238d54ac63a67b6fa35.tar.gz",
        "url_template": "https://github.com/<owner>/<repo>/archive/<rev>.tar.gz"
    },
    "nixpkgs": {
        "branch": "nixos-unstable-small",
        "description": "Nix Packages collection",
        "homepage": null,
        "owner": "NixOS",
        "repo": "nixpkgs",
        "rev": "16477d764f375ef7b81acbfd13189299ff67f233",
        "sha256": "059wgip4g7na4f8rmi0k8j0pqxpaxgm8mircd4j3rmq6bb80f9z1",
        "type": "tarball",
        "url": "https://github.com/NixOS/nixpkgs/archive/16477d764f375ef7b81acbfd13189299ff67f233.tar.gz",
        "url_template": "https://github.com/<owner>/<repo>/archive/<rev>.tar.gz"
    },
    "nixpkgs-mozilla": {
        "branch": "master",
        "description": "mozilla related nixpkgs (extends nixos/nixpkgs repo)",
        "homepage": null,
        "owner": "mozilla",
        "repo": "nixpkgs-mozilla",
        "rev": "e912ed483e980dfb4666ae0ed17845c4220e5e7c",
        "sha256": "08fvzb8w80bkkabc1iyhzd15f4sm7ra10jn32kfch5klgl0gj3j3",
        "type": "tarball",
        "url": "https://github.com/mozilla/nixpkgs-mozilla/archive/e912ed483e980dfb4666ae0ed17845c4220e5e7c.tar.gz",
        "url_template": "https://github.com/<owner>/<repo>/archive/<rev>.tar.gz"
    },
    "nixpkgs-stable": {
        "branch": "nixos-20.03",
        "description": "Nix Packages collection",
        "homepage": null,
        "owner": "NixOS",
        "repo": "nixpkgs",
        "rev": "a438aed5a6ceda6beaa998af1c67a38f4b4c3156",
        "sha256": "0di45qxffbqpn0rwzaq20dlm25asvwfwqwy66zysrxq8xgk8vjll",
        "type": "tarball",
        "url": "https://github.com/NixOS/nixpkgs/archive/a438aed5a6ceda6beaa998af1c67a38f4b4c3156.tar.gz",
        "url_template": "https://github.com/<owner>/<repo>/archive/<rev>.tar.gz"
    },
    "notify-send.sh": {
        "branch": "master",
        "description": "drop-in replacement for notify-send with more features",
        "homepage": null,
        "owner": "vlevit",
        "repo": "notify-send.sh",
        "rev": "7ae815c1aba8356f5ca8f123e5127749e671cd59",
        "sha256": "09z5998jda7q8h9r8rsp60hhwsnyl6cvkl6f0rl0h466bllx3mq2",
        "type": "tarball",
        "url": "https://github.com/vlevit/notify-send.sh/archive/7ae815c1aba8356f5ca8f123e5127749e671cd59.tar.gz",
        "url_template": "https://github.com/<owner>/<repo>/archive/<rev>.tar.gz"
    }
}
